<!--

This xml fragment defines local subject code keywords for Founders and Survivors
S. Silcot
V 1.0 March 2011

-->
<list id="local-subject-codes.xml" type="rif-cs local subject types for FAS" n="User can select zero or more of these">

  <item>
    <code>ai</code>
    <desc>Fas record type for TAHO/Archive Office of Tasmania index of convicts</desc>
  </item>

  <item>
    <code>b4a</code>
    <desc>Fas record type for Bateson 4th edition convict ships</desc>
  </item>

  <item>
    <code>crs</code>
    <desc>Fas record type for transcription of complete conduct records 1 in 25 sample</desc>
  </item>

  <item>
    <code>c23a</code>
    <desc>Fas record type for transcription of CON23 (partial)</desc>
  </item>

  <item>
    <code>c31a</code>
    <desc>Fas record type for transcription of CON31 (complete) male conduct records</desc>
  </item>

  <item>
    <code>mm</code>
    <desc>Fas record type for transcription of male musters</desc>
  </item>

  <item>
    <code>c33a</code>
    <desc>Fas record type for transcription of CON33 (partial to fill gaps in "om")</desc>
  </item>

  <item>
    <code>om</code>
    <desc>Fas record type for D. Oxley's MS Access database of male convict indents CON14</desc>
  </item>

  <item>
    <code>dlm</code>
    <desc>Fas record type for transcription of CON18 (description lists)</desc>
  </item>

  <item>
    <code>dcm</code>
    <desc>Fas record type for transcription of male convict deaths consolidated from various sources</desc>
  </item>

  <item>
    <code>c40a</code>
    <desc>Fas record type for transcription of CON40 (complete) female conduct records</desc>
  </item>

  <item>
    <code>mf</code>
    <desc>Fas record type for transcription of female convict musters</desc>
  </item>

  <item>
    <code>dlf</code>
    <desc>Fas record type for transcription of CON19 (description lists) for women</desc>
  </item>

  <item>
    <code>of</code>
    <desc>Fas record type for D. Oxley's MS Access database of female convict indents CON15</desc>
  </item>

  <item>
    <code>dcf</code>
    <desc>Fas record type for transcription of female convict deaths consolidated from various sources</desc>
  </item>

  <item>
    <code>di</code>
    <desc>Fas record type for TAHO/Archive Office of Tasmania departures index</desc>
  </item>

  <item>
    <code>hga</code>
    <desc>Fas record type for transcription of Hobart Town Gazette absconder/recapture notices</desc>
  </item>

  <item>
    <code>hgf</code>
    <desc>Fas record type for transcription of Hobart Town Gazette freedom and police appointment/revokation notices</desc>
  </item>

  <item>
    <code>kgb</code>
    <desc>Fas record type for births from R.Kippen and P.Gunn Tasmanian civil Births, Deaths, Marriages register 1838-1899</desc>
  </item>

  <item>
    <code>kgm</code>
    <desc>Fas record type for marriages from R.Kippen and P.Gunn Tasmanian civil Births, Deaths, Marriages register 1838-1899</desc>
  </item>

  <item>
    <code>transcription</code>
    <desc>Indicates data transcribed by the FAS project</desc>
  </item>

  <item>
    <code>male convicts</code>
    <desc>Male convicts</desc>
  </item>

  <item>
    <code>female convicts</code>
    <desc>Female convicts</desc>
  </item>

</list>
